odoo/addons/crm_lead_attach_related_saleorder_report/README.rst
odoo/addons/crm_lead_attach_related_saleorder_report/__init__.py
odoo/addons/crm_lead_attach_related_saleorder_report/__manifest__.py
odoo/addons/crm_lead_attach_related_saleorder_report/i18n/ca_ES.po
odoo/addons/crm_lead_attach_related_saleorder_report/i18n/es.po
odoo/addons/crm_lead_attach_related_saleorder_report/models/__init__.py
odoo/addons/crm_lead_attach_related_saleorder_report/models/crm_lead.py
odoo/addons/crm_lead_attach_related_saleorder_report/models/mail_compose_message.py
odoo/addons/crm_lead_attach_related_saleorder_report/readme/CONTRIBUTORS.md
odoo/addons/crm_lead_attach_related_saleorder_report/readme/CREDITS.md
odoo/addons/crm_lead_attach_related_saleorder_report/readme/DESCRIPTION.md
odoo/addons/crm_lead_attach_related_saleorder_report/readme/USAGE.md
odoo/addons/crm_lead_attach_related_saleorder_report/static/description/icon.png
odoo/addons/crm_lead_attach_related_saleorder_report/static/description/index.html
odoo/addons/crm_lead_attach_related_saleorder_report/tests/__init__.py
odoo/addons/crm_lead_attach_related_saleorder_report/tests/test_crm_lead_attach_related_saleorder_report.py
odoo/addons/crm_lead_attach_related_saleorder_report/views/crm_lead.xml
odoo/addons/crm_lead_attach_related_saleorder_report/views/mail_compose_message.xml
odoo_addon_crm_lead_attach_related_saleorder_report-17.0.1.1.0.dist-info/METADATA
odoo_addon_crm_lead_attach_related_saleorder_report-17.0.1.1.0.dist-info/WHEEL
odoo_addon_crm_lead_attach_related_saleorder_report-17.0.1.1.0.dist-info/top_level.txt
odoo_addon_crm_lead_attach_related_saleorder_report-17.0.1.1.0.dist-info/RECORD
