Metadata-Version: 2.1
Name: odoo-addon-crm_lead_attach_related_saleorder_report
Version: 17.0.1.1.0
Requires-Python: >=3.10
Requires-Dist: odoo>=17.0a,<17.1dev
Summary: Allow to attach sale documents into the opportunity and send them.
Home-page: https://github.com/sygel-technology/sy-crm
License: AGPL-3
Author: Sygel
Classifier: Programming Language :: Python
Classifier: Framework :: Odoo
Classifier: Framework :: Odoo :: 17.0
Classifier: License :: OSI Approved :: GNU Affero General Public License v3
